LICENSE
MANIFEST.in
README.rst
setup.py
cotoolz/__init__.py
cotoolz/_coiter.c
cotoolz/_comap.c
cotoolz/_cozip.c
cotoolz/_emptycoroutine.c
cotoolz/curried.py
cotoolz.egg-info/PKG-INFO
cotoolz.egg-info/SOURCES.txt
cotoolz.egg-info/dependency_links.txt
cotoolz.egg-info/pbr.json
cotoolz.egg-info/requires.txt
cotoolz.egg-info/top_level.txt
cotoolz/include/__init__.py
cotoolz/include/cotoolz/__init__.py
cotoolz/include/cotoolz/coiter.h
cotoolz/include/cotoolz/comap.h
cotoolz/include/cotoolz/cotoolz.h
cotoolz/include/cotoolz/cozip.h
cotoolz/include/cotoolz/emptycoroutine.h
cotoolz/tests/test_coiter.py
cotoolz/tests/test_comap.py
cotoolz/tests/test_cozip.py
cotoolz/tests/test_emptycoroutine.py