Metadata-Version: 1.1
Name: cotoolz
Version: 0.1.5
Summary: A set of utility functions for coroutines.
Home-page: https://github.com/llllllllll/cotoolz
Author: Joe Jevnik
Author-email: joejev@gmail.com
License: GPL-2
Platform: UNKNOWN
Classifier: Development Status :: 3 - Alpha
Classifier: License :: OSI Approved :: GNU General Public License v2 (GPLv2)
Classifier: Intended Audience :: Developers
Classifier: Natural Language :: English
Classifier: Programming Language :: Python :: 3 :: Only
Classifier: Programming Language :: Python :: 3.4
Classifier: Programming Language :: Python :: 3.5
Classifier: Programming Language :: Python :: Implementation :: CPython
Classifier: Operating System :: POSIX
Classifier: Topic :: Software Development
Classifier: Topic :: Utilities
